cloudmesh_client/__init__.py
cloudmesh_client/default.py
cloudmesh_client/exc.py
cloudmesh_client/locations.py
cloudmesh_client/logger.py
cloudmesh_client/main.py
cloudmesh_client/setup.py
cloudmesh_client/shell_commad.py
cloudmesh_client/var.py
cloudmesh_client/version.py
cloudmesh_client/api/__init__.py
cloudmesh_client/api/impl/__init__.py
cloudmesh_client/api/impl/openstack.py
cloudmesh_client/cloud/ListResource.py
cloudmesh_client/cloud/__init__.py
cloudmesh_client/cloud/attributes.py
cloudmesh_client/cloud/counter.py
cloudmesh_client/cloud/experiment.py
cloudmesh_client/cloud/flavor.py
cloudmesh_client/cloud/group.py
cloudmesh_client/cloud/hpc.py
cloudmesh_client/cloud/image.py
cloudmesh_client/cloud/inventory.py
cloudmesh_client/cloud/ip.py
cloudmesh_client/cloud/key.py
cloudmesh_client/cloud/launcher.py
cloudmesh_client/cloud/limits.py
cloudmesh_client/cloud/list.py
cloudmesh_client/cloud/network.py
cloudmesh_client/cloud/nova.py
cloudmesh_client/cloud/quota.py
cloudmesh_client/cloud/register.py
cloudmesh_client/cloud/reservation.py
cloudmesh_client/cloud/secgroup.py
cloudmesh_client/cloud/stack.py
cloudmesh_client/cloud/sync.py
cloudmesh_client/cloud/usage.py
cloudmesh_client/cloud/vc.py
cloudmesh_client/cloud/vm.py
cloudmesh_client/cloud/workflow.py
cloudmesh_client/cloud/hpc/BatchProvider.py
cloudmesh_client/cloud/hpc/BatchProviderBase.py
cloudmesh_client/cloud/hpc/__init__.py
cloudmesh_client/cloud/hpc/provider/__init__.py
cloudmesh_client/cloud/hpc/provider/slurm/BatchProviderSLURM.py
cloudmesh_client/cloud/hpc/provider/slurm/__init__.py
cloudmesh_client/cloud/hpc/provider/slurm/squeue.py
cloudmesh_client/cloud/iaas/CloudProvider.py
cloudmesh_client/cloud/iaas/CloudProviderBase.py
cloudmesh_client/cloud/iaas/__init__.py
cloudmesh_client/cloud/iaas/provider/__init__.py
cloudmesh_client/cloud/iaas/provider/aws/CloudProviderAwsAPI.py
cloudmesh_client/cloud/iaas/provider/aws/__init__.py
cloudmesh_client-4.7.3.dist-info/DESCRIPTION.rst
cloudmesh_client-4.7.3.dist-info/METADATA
cloudmesh_client-4.7.3.dist-info/RECORD
cloudmesh_client-4.7.3.dist-info/WHEEL
cloudmesh_client-4.7.3.dist-info/entry_points.txt
cloudmesh_client-4.7.3.dist-info/metadata.json
cloudmesh_client-4.7.3.dist-info/top_level.txt
