Metadata-Version: 2.0
Name: cloudmesh-client
Version: 4.7.3
Summary: cloudmesh_client - A heterogeneous multi cloud command client and shell
Home-page: https://github.com/cloudmesh/cloudmesh_client
Author: Gregor von Laszewski
Author-email: laszewski@gmail.com
License: Apache License, Version 2.0
Keywords: cloud cmd commandshell plugins
Platform: UNKNOWN
Classifier: Intended Audience :: Developers
Classifier: Intended Audience :: Education
Classifier: Intended Audience :: Science/Research
Classifier: Development Status :: 2 - Pre-Alpha
Classifier: Intended Audience :: Developers
Classifier: License :: OSI Approved :: Apache Software License
Classifier: Operating System :: MacOS :: MacOS X
Classifier: Operating System :: POSIX :: Linux
Classifier: Programming Language :: Python :: 2.7
Classifier: Topic :: Scientific/Engineering
Classifier: Topic :: System :: Clustering
Classifier: Topic :: System :: Distributed Computing
Classifier: Topic :: Software Development :: Libraries :: Python Modules
Classifier: Environment :: Console
Requires-Dist: Babel (==2.3.4)
Requires-Dist: Flask (==0.12)
Requires-Dist: Flask-Admin (==1.4.2)
Requires-Dist: Flask-HTTPAuth (==3.2.2)
Requires-Dist: Flask-SQLAlchemy (==2.1)
Requires-Dist: Jinja2 (==2.8.1)
Requires-Dist: MarkupSafe (==0.23)
Requires-Dist: PyYAML (==3.12)
Requires-Dist: SQLAlchemy (==1.1.5)
Requires-Dist: WTForms (==2.1)
Requires-Dist: Werkzeug (==0.11.15)
Requires-Dist: ansible (==2.2.1.0)
Requires-Dist: apache-libcloud (==1.5.0)
Requires-Dist: appdirs (==1.4.0)
Requires-Dist: azure (==1.0.3)
Requires-Dist: azure-common (==1.1.4)
Requires-Dist: azure-mgmt (==0.20.2)
Requires-Dist: azure-mgmt-common (==0.20.0)
Requires-Dist: azure-mgmt-compute (==0.20.1)
Requires-Dist: azure-mgmt-network (==0.20.1)
Requires-Dist: azure-mgmt-nspkg (==1.0.0)
Requires-Dist: azure-mgmt-resource (==0.20.1)
Requires-Dist: azure-mgmt-storage (==0.20.0)
Requires-Dist: azure-nspkg (==1.0.0)
Requires-Dist: azure-servicebus (==0.20.1)
Requires-Dist: azure-servicemanagement-legacy (==0.20.2)
Requires-Dist: azure-storage (==0.20.3)
Requires-Dist: cffi (==1.9.1)
Requires-Dist: click (==6.7)
Requires-Dist: cloudmesh-timestring (==1.6.2.1)
Requires-Dist: colorama (==0.3.7)
Requires-Dist: cryptography (==1.7.2)
Requires-Dist: debtcollector (==1.11.0)
Requires-Dist: docopt (==0.6.2)
Requires-Dist: enum34 (==1.1.6)
Requires-Dist: funcsigs (==1.0.2)
Requires-Dist: functools32 (==3.2.3.post2)
Requires-Dist: future (==0.16.0)
Requires-Dist: futures (==3.0.5)
Requires-Dist: gitchangelog (==2.4.1)
Requires-Dist: httpsig (==1.1.2)
Requires-Dist: humanize (==0.5.1)
Requires-Dist: idna (==2.2)
Requires-Dist: ipaddress (==1.0.18)
Requires-Dist: iso8601 (==0.1.11)
Requires-Dist: itsdangerous (==0.24)
Requires-Dist: jsonschema (==2.5.1)
Requires-Dist: keystoneauth1 (==2.18.0)
Requires-Dist: monotonic (==1.2)
Requires-Dist: msgpack-python (==0.4.8)
Requires-Dist: netaddr (==0.7.19)
Requires-Dist: netifaces (==0.10.5)
Requires-Dist: nose (==1.3.7)
Requires-Dist: oslo.config (==3.22.0)
Requires-Dist: oslo.i18n (==3.12.0)
Requires-Dist: oslo.serialization (==2.16.0)
Requires-Dist: oslo.utils (==3.22.0)
Requires-Dist: packaging (==16.8)
Requires-Dist: paramiko (==2.1.1)
Requires-Dist: pbr (==1.10.0)
Requires-Dist: positional (==1.1.1)
Requires-Dist: prettytable (==0.7.2)
Requires-Dist: py (==1.4.32)
Requires-Dist: pyaml (==16.12.2)
Requires-Dist: pyasn1 (==0.1.9)
Requires-Dist: pycparser (==2.17)
Requires-Dist: pycrypto (==2.6.1)
Requires-Dist: pyparsing (==2.1.10)
Requires-Dist: pyreadline (==2.1)
Requires-Dist: pytest (==3.0.6)
Requires-Dist: python-dateutil (==2.6.0)
Requires-Dist: python-hostlist (==1.17)
Requires-Dist: python-keystoneclient (==3.10.0)
Requires-Dist: python-novaclient (==7.1.0)
Requires-Dist: pytz (==2016.10)
Requires-Dist: requests (==2.13.0)
Requires-Dist: rfc3986 (==0.4.1)
Requires-Dist: sandman (==0.9.8)
Requires-Dist: simplejson (==3.10.0)
Requires-Dist: six (==1.10.0)
Requires-Dist: stevedore (==1.20.0)
Requires-Dist: urllib3 (==1.20)
Requires-Dist: wrapt (==1.10.8)
